fastapi_mongodb_utils/__init__.py
fastapi_mongodb_utils/date.py
fastapi_mongodb_utils/fastapi.py
fastapi_mongodb_utils-0.3.0.dist-info/LICENSE
fastapi_mongodb_utils-0.3.0.dist-info/METADATA
fastapi_mongodb_utils-0.3.0.dist-info/WHEEL
fastapi_mongodb_utils-0.3.0.dist-info/RECORD
